README.txt
setup.py
collective/__init__.py
collective.formlib.link.egg-info/PKG-INFO
collective.formlib.link.egg-info/SOURCES.txt
collective.formlib.link.egg-info/dependency_links.txt
collective.formlib.link.egg-info/entry_points.txt
collective.formlib.link.egg-info/namespace_packages.txt
collective.formlib.link.egg-info/not-zip-safe
collective.formlib.link.egg-info/requires.txt
collective.formlib.link.egg-info/top_level.txt
collective/formlib/__init__.py
collective/formlib/link/__init__.py
collective/formlib/link/configure.zcml
collective/formlib/link/field.py
collective/formlib/link/interfaces.py
collective/formlib/link/tests.py
collective/formlib/link/utils.py
collective/formlib/link/widget.py