Metadata-Version: 1.0
Name: collective.formlib.link
Version: 0.2
Summary: A link schema type representing an internal or external link.
Home-page: UNKNOWN
Author: Malthe Borch
Author-email: mborch@gmail.com
License: GPL
Platform: UNKNOWN
Classifier: Framework :: Plone
Classifier: Framework :: Zope2
Classifier: Framework :: Zope3
Classifier: Programming Language :: Python
Classifier: Topic :: Software Development :: Libraries :: Python Modules
